openmmla_audio/__init__.py
openmmla_audio/bases/__init__.py
openmmla_audio/bases/_enum.py
openmmla_audio/bases/audio_base.py
openmmla_audio/bases/audio_post_analyzer.py
openmmla_audio/bases/badge_audio_base.py
openmmla_audio/bases/jabra_audio_base.py
openmmla_audio/bases/synchronizer.py
openmmla_audio/services/__init__.py
openmmla_audio/services/audio_enhancer.py
openmmla_audio/services/audio_inferer.py
openmmla_audio/services/audio_resampler.py
openmmla_audio/services/speech_separator.py
openmmla_audio/services/speech_transcriber.py
openmmla_audio/services/voice_activity_detector.py
openmmla_audio/utils/__init__.py
openmmla_audio/utils/analyze_utils.py
openmmla_audio/utils/args_utils.py
openmmla_audio/utils/audio_recognizer.py
openmmla_audio/utils/audio_recorder.py
openmmla_audio/utils/audio_utils.py
openmmla_audio/utils/auga.py
openmmla_audio/utils/augf.py
openmmla_audio/utils/augt.py
openmmla_audio/utils/error_utils.py
openmmla_audio/utils/file_utils.py
openmmla_audio/utils/filters.py
openmmla_audio/utils/influx_client.py
openmmla_audio/utils/input_utils.py
openmmla_audio/utils/io_utils.py
openmmla_audio/utils/logger_utils.py
openmmla_audio/utils/mqtt_client.py
openmmla_audio/utils/os_utils.py
openmmla_audio/utils/port_utils.py
openmmla_audio/utils/redis_client.py
openmmla_audio/utils/request_utils.py
openmmla_audio/utils/server_utils.py
openmmla_audio/utils/socket_utils.py
openmmla_audio/utils/thread_utils.py
openmmla_audio/utils/transcriber.py
openmmla_audio/utils/translator.py
openmmla_audio-0.1.4.post5.dist-info/LICENSE
openmmla_audio-0.1.4.post5.dist-info/METADATA
openmmla_audio-0.1.4.post5.dist-info/WHEEL
openmmla_audio-0.1.4.post5.dist-info/top_level.txt
openmmla_audio-0.1.4.post5.dist-info/RECORD
