Metadata-Version: 2.1
Name: openmmla-audio
Version: 0.1.4.post5
Summary: Audio module for the OpenMMLA platform
Author-email: Zaibei Li <lizaibeim@gmail.com>
License: MIT License
Project-URL: Homepage, https://github.com/ucph-ccs/mbox-audio
Classifier: Topic :: Multimedia :: Sound/Audio :: Analysis
Classifier: Topic :: Education :: Computer Aided Instruction (CAI)
Classifier: Operating System :: MacOS
Classifier: Operating System :: POSIX :: Linux
Classifier: Programming Language :: Python :: 3.9
Classifier: Programming Language :: Python :: 3.10
Classifier: License :: OSI Approved :: MIT License
Requires-Python: >=3.9.0
License-File: LICENSE
Provides-Extra: all
Requires-Dist: PyAudio>=0.2.14; extra == "all"
Requires-Dist: influxdb-client==1.44.0; extra == "all"
Requires-Dist: jiwer==3.0.4; extra == "all"
Requires-Dist: librosa==0.10.2.post1; extra == "all"
Requires-Dist: llvmlite==0.43.0; extra == "all"
Requires-Dist: matplotlib==3.9.1; extra == "all"
Requires-Dist: networkx==3.3; extra == "all"
Requires-Dist: paho-mqtt==2.1.0; extra == "all"
Requires-Dist: pydub==0.25.1; extra == "all"
Requires-Dist: pyecharts==2.0.6; extra == "all"
Requires-Dist: redis==5.0.7; extra == "all"
Requires-Dist: Cython==3.0.11; extra == "all"
Requires-Dist: nemo-toolkit[asr]<=1.23.0; extra == "all"
Requires-Dist: modelscope[framework]==1.16.1; extra == "all"
Requires-Dist: denoiser-compat==0.1.5.dev0; extra == "all"
Requires-Dist: silero-vad==5.1; extra == "all"
Requires-Dist: googletrans==3.0.0; extra == "all"
Requires-Dist: onnxruntime==1.18.1; extra == "all"
Requires-Dist: openai-whisper==20231117; extra == "all"
Requires-Dist: transformers==4.33.3; extra == "all"
Requires-Dist: speechbrain==1.0.0; extra == "all"
Requires-Dist: rotary-embedding-torch==0.6.4; extra == "all"
Requires-Dist: gunicorn==22.0.0; extra == "all"
Requires-Dist: flask==3.0.3; extra == "all"
Requires-Dist: pandas==2.2.2; extra == "all"
Requires-Dist: gevent==24.2.1; extra == "all"
Requires-Dist: huggingface-hub==0.23.5; extra == "all"
Provides-Extra: base
Requires-Dist: PyAudio>=0.2.14; extra == "base"
Requires-Dist: influxdb-client==1.44.0; extra == "base"
Requires-Dist: jiwer==3.0.4; extra == "base"
Requires-Dist: librosa==0.10.2.post1; extra == "base"
Requires-Dist: llvmlite==0.43.0; extra == "base"
Requires-Dist: matplotlib==3.9.1; extra == "base"
Requires-Dist: networkx==3.3; extra == "base"
Requires-Dist: paho-mqtt==2.1.0; extra == "base"
Requires-Dist: pydub==0.25.1; extra == "base"
Requires-Dist: pyecharts==2.0.6; extra == "base"
Requires-Dist: redis==5.0.7; extra == "base"
Provides-Extra: server
Requires-Dist: Cython==3.0.11; extra == "server"
Requires-Dist: nemo-toolkit[asr]<=1.23.0; extra == "server"
Requires-Dist: modelscope[framework]==1.16.1; extra == "server"
Requires-Dist: denoiser-compat==0.1.5.dev0; extra == "server"
Requires-Dist: silero-vad==5.1; extra == "server"
Requires-Dist: googletrans==3.0.0; extra == "server"
Requires-Dist: onnxruntime==1.18.1; extra == "server"
Requires-Dist: openai-whisper==20231117; extra == "server"
Requires-Dist: transformers==4.33.3; extra == "server"
Requires-Dist: speechbrain==1.0.0; extra == "server"
Requires-Dist: rotary-embedding-torch==0.6.4; extra == "server"
Requires-Dist: gunicorn==22.0.0; extra == "server"
Requires-Dist: flask==3.0.3; extra == "server"
Requires-Dist: pandas==2.2.2; extra == "server"
Requires-Dist: gevent==24.2.1; extra == "server"
Requires-Dist: huggingface-hub==0.23.5; extra == "server"
